{
  "swagger": "2.0",
  "info": {
    "title": "PartyApp API",
    "description": "API documentation for PartyApp",
    "version": "1.0.0"
  },
  "host": "localhost:5000",
  "basePath": "/",
  "schemes": [
    "http"
  ],
  "paths": {
    "/users": {
      "get": {
        "description": "",
        "responses": {
          "default": {
            "description": ""
          }
        }
      }
    },
    "/{userid}": {
      "get": {
        "description": "",
        "parameters": [
          {
            "name": "userid",
            "in": "path",
            "required": true,
            "type": "string"
          }
        ],
        "responses": {
          "default": {
            "description": ""
          }
        }
      },
      "put": {
        "description": "",
        "parameters": [
          {
            "name": "userid",
            "in": "path",
            "required": true,
            "type": "string"
          }
        ],
        "responses": {
          "default": {
            "description": ""
          }
        }
      },
      "delete": {
        "description": "",
        "parameters": [
          {
            "name": "userid",
            "in": "path",
            "required": true,
            "type": "string"
          }
        ],
        "responses": {
          "default": {
            "description": ""
          }
        }
      }
    },
    "/user": {
      "post": {
        "description": "",
        "responses": {
          "default": {
            "description": ""
          }
        }
      }
    },
    "/parties": {
      "get": {
        "description": "",
        "responses": {
          "default": {
            "description": ""
          }
        }
      }
    },
    "/{partyid}": {
      "get": {
        "description": "",
        "parameters": [
          {
            "name": "partyid",
            "in": "path",
            "required": true,
            "type": "string"
          }
        ],
        "responses": {
          "default": {
            "description": ""
          }
        }
      },
      "put": {
        "description": "",
        "parameters": [
          {
            "name": "partyid",
            "in": "path",
            "required": true,
            "type": "string"
          }
        ],
        "responses": {
          "default": {
            "description": ""
          }
        }
      },
      "delete": {
        "description": "",
        "parameters": [
          {
            "name": "partyid",
            "in": "path",
            "required": true,
            "type": "string"
          }
        ],
        "responses": {
          "default": {
            "description": ""
          }
        }
      }
    },
    "/party": {
      "post": {
        "description": "",
        "responses": {
          "default": {
            "description": ""
          }
        }
      }
    },
    "/party/{partyId}/participate": {
      "post": {
        "description": "",
        "parameters": [
          {
            "name": "partyId",
            "in": "path",
            "required": true,
            "type": "string"
          }
        ],
        "responses": {
          "default": {
            "description": ""
          }
        }
      }
    },
    "/party/{partyId}/cancel": {
      "post": {
        "description": "",
        "parameters": [
          {
            "name": "partyId",
            "in": "path",
            "required": true,
            "type": "string"
          }
        ],
        "responses": {
          "default": {
            "description": ""
          }
        }
      }
    }
  }
}